clustrix/__init__.py
clustrix/cli.py
clustrix/config.py
clustrix/decorator.py
clustrix/executor.py
clustrix/local_executor.py
clustrix/loop_analysis.py
clustrix/utils.py
clustrix-0.1.1.dist-info/licenses/LICENSE
tests/__init__.py
tests/conftest.py
tests/test_cli.py
tests/test_config.py
tests/test_decorator.py
tests/test_executor.py
tests/test_integration.py
tests/test_local_executor.py
tests/test_utils.py
clustrix-0.1.1.dist-info/METADATA
clustrix-0.1.1.dist-info/WHEEL
clustrix-0.1.1.dist-info/entry_points.txt
clustrix-0.1.1.dist-info/top_level.txt
clustrix-0.1.1.dist-info/RECORD
