Metadata-Version: 2.4
Name: clustrix
Version: 0.1.1
Summary: Seamless distributed computing for Python functions
Home-page: https://github.com/ContextLab/clustrix
Author: Contextual Dynamics Laboratory
Author-email: contextualdynamics@gmail.com
Classifier: Development Status :: 4 - Beta
Classifier: Intended Audience :: Developers
Classifier: Intended Audience :: Science/Research
Classifier: License :: OSI Approved :: MIT License
Classifier: Operating System :: OS Independent
Classifier: Programming Language :: Python :: 3
Classifier: Programming Language :: Python :: 3.8
Classifier: Programming Language :: Python :: 3.9
Classifier: Programming Language :: Python :: 3.10
Classifier: Programming Language :: Python :: 3.11
Classifier: Programming Language :: Python :: 3.12
Classifier: Topic :: Scientific/Engineering
Classifier: Topic :: Software Development :: Libraries :: Python Modules
Classifier: Topic :: System :: Distributed Computing
Requires-Python: >=3.8
License-File: LICENSE
Requires-Dist: paramiko>=2.7.0
Requires-Dist: pyyaml>=5.4.0
Requires-Dist: cloudpickle>=2.0.0
Requires-Dist: dill>=0.3.4
Requires-Dist: click>=8.0.0
Provides-Extra: kubernetes
Requires-Dist: kubernetes>=20.13.0; extra == "kubernetes"
Provides-Extra: dev
Requires-Dist: pytest>=6.0; extra == "dev"
Requires-Dist: pytest-cov>=2.0; extra == "dev"
Requires-Dist: black>=21.0; extra == "dev"
Requires-Dist: flake8>=3.8; extra == "dev"
Requires-Dist: mypy>=0.812; extra == "dev"
Provides-Extra: test
Requires-Dist: pytest>=6.0; extra == "test"
Requires-Dist: pytest-cov>=2.0; extra == "test"
Requires-Dist: coverage>=6.0; extra == "test"
Requires-Dist: pytest-xdist>=2.0; extra == "test"
Requires-Dist: pytest-mock>=3.0; extra == "test"
Provides-Extra: docs
Requires-Dist: sphinx>=4.0; extra == "docs"
Requires-Dist: sphinx-wagtail-theme>=6.0.0; extra == "docs"
Requires-Dist: sphinx-autodoc-typehints>=1.12; extra == "docs"
Requires-Dist: nbsphinx>=0.8; extra == "docs"
Requires-Dist: jupyter>=1.0; extra == "docs"
Requires-Dist: ipython>=7.0; extra == "docs"
Provides-Extra: all
Requires-Dist: kubernetes>=20.13.0; extra == "all"
Requires-Dist: pytest>=6.0; extra == "all"
Requires-Dist: pytest-cov>=2.0; extra == "all"
Requires-Dist: black>=21.0; extra == "all"
Requires-Dist: flake8>=3.8; extra == "all"
Requires-Dist: mypy>=0.812; extra == "all"
Requires-Dist: sphinx>=4.0; extra == "all"
Requires-Dist: sphinx-wagtail-theme>=6.0.0; extra == "all"
Requires-Dist: sphinx-autodoc-typehints>=1.12; extra == "all"
Requires-Dist: nbsphinx>=0.8; extra == "all"
Requires-Dist: jupyter>=1.0; extra == "all"
Requires-Dist: ipython>=7.0; extra == "all"
Dynamic: author
Dynamic: author-email
Dynamic: classifier
Dynamic: description
Dynamic: description-content-type
Dynamic: home-page
Dynamic: license-file
Dynamic: provides-extra
Dynamic: requires-dist
Dynamic: requires-python
Dynamic: summary
